OneNueron/__init__.py
OneNueron/perceptron.py
onenueron_sathishbilli-0.0.3.dist-info/LICENSE
onenueron_sathishbilli-0.0.3.dist-info/METADATA
onenueron_sathishbilli-0.0.3.dist-info/WHEEL
onenueron_sathishbilli-0.0.3.dist-info/top_level.txt
onenueron_sathishbilli-0.0.3.dist-info/RECORD
