Metadata-Version: 2.1
Name: onenueron-sathishbilli
Version: 0.0.3
Summary: this a peceptron package
Home-page: https://github.com/sathishbilli/onenueron
Author: sathishbilli
Author-email: sathishmahi398@gmail.com
License: UNKNOWN
Project-URL: Bug Tracker, https://github.com/sathishbilli/onenueron/issues
Platform: UNKNOWN
Classifier: Programming Language :: Python :: 3
Classifier: License :: OSI Approved :: MIT License
Classifier: Operating System :: OS Independent
Requires-Python: >=3.7
License-File: LICENSE
Requires-Dist: numpy
Requires-Dist: tqdm
